il2pred/Data/merci/MERCI_motif_locator.pl
il2pred/Data/model1/dpc_len_feat_scalar.pkl
il2pred/Data/model1/dpc_len_feat_sel.txt
il2pred/Data/model1/dpc_len_feat_sel_model.pkl
il2pred/Data/model2/dpc_len_feat_scalar.pkl
il2pred/Data/model2/dpc_len_feat_sel.txt
il2pred/Data/model2/dpc_len_feat_sel_model.pkl
il2pred/Data/model3/dpc_len_feat_scalar.pkl
il2pred/Data/model3/dpc_len_feat_sel.txt
il2pred/Data/model3/dpc_len_feat_sel_model.pkl
il2pred/Data/motifs1/neg_motif.txt
il2pred/Data/motifs1/pos_motif.txt
il2pred/Data/motifs2/neg_motif.txt
il2pred/Data/motifs2/pos_motif.txt
il2pred/Data/motifs3/neg_motif.txt
il2pred/Data/motifs3/pos_motif.txt
il2pred/python_script/__init__.py
il2pred/python_script/il2pred.py
il2pred-1.0.5.dist-info/LICENSE.txt
il2pred-1.0.5.dist-info/METADATA
il2pred-1.0.5.dist-info/WHEEL
il2pred-1.0.5.dist-info/entry_points.txt
il2pred-1.0.5.dist-info/top_level.txt
il2pred-1.0.5.dist-info/RECORD
