Metadata-Version: 2.1
Name: il2pred
Version: 1.0.5
Summary: il2pred: A tool for predicting IL2 inducing or non-IL2 inducing peptides
Home-page: https://github.com/namanm04/il2pred
Author: Naman Kumar Mehta
Author-email: namanm@iiitd.ac.in
License: UNKNOWN
Platform: UNKNOWN
Requires-Python: >=3.6
License-File: LICENSE.txt
Requires-Dist: numpy
Requires-Dist: pandas
Requires-Dist: scikit-learn ==1.5.2
Requires-Dist: tqdm
Requires-Dist: joblib
